namehint/__init__.py
namehint/dictionary.json
namehint/namehint.py
namehint-1.0.0.dist-info/METADATA
namehint-1.0.0.dist-info/WHEEL
namehint-1.0.0.dist-info/entry_points.txt
namehint-1.0.0.dist-info/top_level.txt
namehint-1.0.0.dist-info/RECORD
