Metadata-Version: 2.1
Name: namehint
Version: 1.0.0
Summary: A tool that provides English synonyms for Korean words to assist in English naming.
Author: gongboo
Author-email: gongboolearn@gmail.com
Requires-Python: >=3.6
Requires-Dist: jamo
